{
  "card_set": {
    "cards": [
      {
        "card": {
          "address": "Card Title",
          "body": "<p>Nullam quis risus eget urna mollis ornare vel eu leo. Aenean lacinia bibendum nulla sed consectetur.</p>",
          "image": {
            "src": "../../images/card-image-fpo.png",
            "alt": ""
          },
          "status_label": "Auction",
          "status_detail": "06/17/2023"
        }
      },
      {
        "card": {
          "address": "Card Title",
          "body": "<p>Nullam quis risus eget urna mollis ornare vel eu leo. Aenean lacinia bibendum nulla sed consectetur.</p>",
          "image": {
            "src": "../../images/card-image-fpo.png",
            "alt": ""
          },
          "status_label": "Auction",
          "status_detail": "06/17/2023"
        }
      },
      {
        "card": {
          "address": "Card Title",
          "body": "<p>Nullam quis risus eget urna mollis ornare vel eu leo. Aenean lacinia bibendum nulla sed consectetur.</p>",
          "image": {
            "src": "../../images/card-image-fpo.png",
            "alt": ""
          },
          "status_label": "Auction",
          "status_detail": "06/17/2023"
        }
      },

      {
        "card": {
          "address": "Card Title",
          "body": "<p>Nullam quis risus eget urna mollis ornare vel eu leo. Aenean lacinia bibendum nulla sed consectetur.</p>",
          "image": {
            "src": "",
            "alt": ""
          },
          "status_label": "Auction",
          "status_detail": "06/17/2023"
        }
      },
      {
        "card": {
          "address": "Card Title Lorem Ipsum Dolor Sit Amet",
          "body": "<p>Nullam quis risus eget urna mollis ornare vel eu leo. Aenean lacinia bibendum nulla sed consectetur.</p>",
          "image": {
            "src": "",
            "alt": ""
          },
          "status_label": "Auction",
          "status_detail": "06/17/2023"
        }
      }
    ]
  }
}
